fivitech_mt5_connector/__init__.py
fivitech_mt5_connector/apps.py
fivitech_mt5_connector/constants.py
fivitech_mt5_connector/exceptions.py
fivitech_mt5_connector/interface.py
fivitech_mt5_connector/pool.py
fivitech_mt5_connector/sinks.py
fivitech_mt5_connector/utils.py
fivitech_mt5_connector/views.py
fivitech_mt5_connector/connection/__init__.py
fivitech_mt5_connector/connection/auth.py
fivitech_mt5_connector/connection/manager.py
fivitech_mt5_connector/helpers/__init__.py
fivitech_mt5_connector/helpers/base.py
fivitech_mt5_connector/helpers/deal.py
fivitech_mt5_connector/helpers/order.py
fivitech_mt5_connector/helpers/position.py
fivitech_mt5_connector/helpers/transaction.py
fivitech_mt5_connector/helpers/user.py
fivitech_mt5_connector-0.2.19.dist-info/METADATA
fivitech_mt5_connector-0.2.19.dist-info/WHEEL
fivitech_mt5_connector-0.2.19.dist-info/top_level.txt
fivitech_mt5_connector-0.2.19.dist-info/RECORD
