Metadata-Version: 2.4
Name: fivitech-mt5-connector
Version: 0.2.19
Summary: A private MetaTrader5 connection and management package
Home-page: https://github.com/fivitech/mt5-connector
Author: Fivitech
Author-email: contact@fivitech.com
Classifier: Development Status :: 4 - Beta
Classifier: Intended Audience :: Developers
Classifier: Topic :: Software Development :: Libraries :: Python Modules
Classifier: Programming Language :: Python :: 3.7
Classifier: Programming Language :: Python :: 3.8
Classifier: Programming Language :: Python :: 3.9
Classifier: Programming Language :: Python :: 3.10
Classifier: Operating System :: OS Independent
Requires-Python: >=3.7
Requires-Dist: MT5Manager>=5.0.3906
Requires-Dist: pandas>=1.0.0
Requires-Dist: numpy>=1.19.0
Requires-Dist: pytz>=2021.1
Requires-Dist: requests>=2.26.0
Requires-Dist: python-dateutil>=2.8.2
Requires-Dist: tenacity>=8.2.3
Provides-Extra: dev
Requires-Dist: build>=1.0.0; extra == "dev"
Requires-Dist: twine>=4.0.0; extra == "dev"
Requires-Dist: pytest>=7.0.0; extra == "dev"
Requires-Dist: black>=22.0.0; extra == "dev"
Requires-Dist: flake8>=4.0.0; extra == "dev"
Dynamic: author
Dynamic: author-email
Dynamic: classifier
Dynamic: description
Dynamic: description-content-type
Dynamic: home-page
Dynamic: provides-extra
Dynamic: requires-dist
Dynamic: requires-python
Dynamic: summary
